{
  "description": "1V1 连线桌游微信小程序 v1.0",
  "packOptions": {
    "ignore": [],
    "include": []
  },
  "setting": {
    "bundle": false,
    "userConfirmedBundleSwitch": false,
    "urlCheck": false,
    "scopeDataCheck": false,
    "coverView": true,
    "es6": true,
    "postcss": true,
    "compileHotReLoad": false,
    "lazyloadPlaceholderEnable": false,
    "preloadBackgroundData": false,
    "minified": false,
    "autoAudits": false,
    "newFeature": false,
    "uglifyFileName": false,
    "uploadWithSourceMap": true,
    "useIsolateContext": true,
    "nodeModules": false,
    "enhance": true,
    "useMultiFrameRuntime": true,
    "showShadowRootInWxmlPanel": true,
    "packNpmManually": false,
    "packNpmRelationList": [],
    "minifyWXSS": false,
    "showES6CompileOption": false,
    "minifyWXML": false,
    "babelSetting": {
      "ignore": [],
      "disablePlugins": [],
      "outputPath": ""
    }
  },
  "compileType": "miniprogram",
  "libVersion": "2.19.4",
  "appid": "touristappid",
  "projectname": "wechat-link-game",
  "condition": {},
  "editorSetting": {
    "tabIndent": "insertSpaces",
    "tabSize": 2
  }
}
